coparun_module.cpython-312-aarch64-linux-musl.so
copapy/__init__.py
copapy/_autograd.py
copapy/_basic_types.py
copapy/_binwrite.py
copapy/_compiler.py
copapy/_helper_types.py
copapy/_math.py
copapy/_matrices.py
copapy/_mixed.py
copapy/_stencils.py
copapy/_target.py
copapy/_vectors.py
copapy/backend.py
copapy/filters.py
copapy/py.typed
copapy/_vendor/pelfy/__init__.py
copapy/_vendor/pelfy/_fields_data.py
copapy/_vendor/pelfy/_main.py
copapy/_vendor/pelfy/_output_formatter.py
copapy/_vendor/pelfy/py.typed
copapy/obj/stencils_arm64_O3.o
copapy/obj/stencils_armv6_O3.o
copapy/obj/stencils_armv7_O3.o
copapy/obj/stencils_x86_64_O3.o
copapy/obj/stencils_x86_O3.o
coparun/coparun_module.c
coparun/mem_man.c
coparun/runmem.c
copapy-0.0.3.dist-info/METADATA
copapy-0.0.3.dist-info/WHEEL
copapy-0.0.3.dist-info/top_level.txt
copapy-0.0.3.dist-info/RECORD
copapy-0.0.3.dist-info/licenses/LICENSE
