Metadata-Version: 2.4
Name: copapy
Version: 0.0.3
Summary: Copy-Patch Compiler
Author-email: Nicolas Kruse <nicolas.kruse@nonan.net>
License-Expression: MIT
Project-URL: Homepage, https://github.com/nonannet/copapy
Project-URL: Issues, https://github.com/nonannet/copapy/issues
Classifier: Programming Language :: Python :: 3
Classifier: Operating System :: OS Independent
Requires-Python: >=3.10
License-File: LICENSE
Provides-Extra: dev
Requires-Dist: ruff; extra == "dev"
Requires-Dist: mypy; extra == "dev"
Requires-Dist: pytest; extra == "dev"
Requires-Dist: pelfy>=1.0.7; extra == "dev"
Provides-Extra: doc-build
Requires-Dist: sphinx; extra == "doc-build"
Requires-Dist: pydata_sphinx_theme; extra == "doc-build"
Requires-Dist: sphinx-autodoc-typehints; extra == "doc-build"
Requires-Dist: myst-parser; extra == "doc-build"
Requires-Dist: pelfy>=1.0.7; extra == "doc-build"
Dynamic: license-file
